spllib/__init__.py
spllib/spllib.py
splllib/__init__.py
splllib/spllib.py
spllib_elunico-0.0.5.dist-info/LICENSE
spllib_elunico-0.0.5.dist-info/METADATA
spllib_elunico-0.0.5.dist-info/WHEEL
spllib_elunico-0.0.5.dist-info/top_level.txt
spllib_elunico-0.0.5.dist-info/RECORD
