Metadata-Version: 2.1
Name: spllib-elunico
Version: 0.0.5
Summary: Library for parsing and writing Simple Property List (SPL) files 
Home-page: https://github.com/elunico/spllib
Author: Thomas Povinelli
Author-email: tompov227@gmail.com
Classifier: Programming Language :: Python :: 3
Classifier: License :: OSI Approved :: MIT License
Classifier: Operating System :: OS Independent
Requires-Python: >=3.10
License-File: LICENSE
